pyinvesting/__init__.py
pyinvesting/history.py
pyinvesting/online.py
pyinvesting/online_scrapping.py
pyinvesting/online_websocket.py
pyinvesting/search.py
pyinvesting-0.31.dist-info/LICENSE
pyinvesting-0.31.dist-info/METADATA
pyinvesting-0.31.dist-info/WHEEL
pyinvesting-0.31.dist-info/top_level.txt
pyinvesting-0.31.dist-info/RECORD
