Metadata-Version: 2.1
Name: pyinvesting
Version: 0.31
Summary: Investing.com API - Market and historical data downloader
Home-page: https://github.com/crapher/pyinvesting
Author: Diego Degese
Author-email: ddegese@gmail.com
License: Apache
Keywords: pandas,investing,online,historical,downloader,finance
Platform: any
Classifier: License :: OSI Approved :: Apache Software License
Classifier: Development Status :: 3 - Alpha
Classifier: Operating System :: OS Independent
Classifier: Intended Audience :: Developers
Classifier: Topic :: Office/Business :: Financial
Classifier: Topic :: Office/Business :: Financial :: Investment
Classifier: Topic :: Scientific/Engineering :: Interface Engine/Protocol Translator
Classifier: Topic :: Software Development :: Libraries
Classifier: Topic :: Software Development :: Libraries :: Python Modules
Classifier: Programming Language :: Python :: 3
Classifier: Programming Language :: Python :: 3.6
Classifier: Programming Language :: Python :: 3.7
Classifier: Programming Language :: Python :: 3.8
Requires-Dist: pandas (>=1.0.0)
Requires-Dist: numpy (>=1.18.1)
Requires-Dist: requests (>=2.21.0)
Requires-Dist: websocket-client (>=0.57.0)
Requires-Dist: pyquery (>=1.2)
